geringoso.py
geringoso-0.1.1.dist-info/LICENSE
geringoso-0.1.1.dist-info/METADATA
geringoso-0.1.1.dist-info/WHEEL
geringoso-0.1.1.dist-info/entry_points.txt
geringoso-0.1.1.dist-info/top_level.txt
geringoso-0.1.1.dist-info/RECORD
